{
  "$schema": "https://ui.shadcn.com/schema/registry-item.json",
  "name": "eslint",
  "type": "registry:item",
  "title": "ESLint configuration",
  "description": "ESLint configuration for Next.js, TypeScript, and Shadcn UI",
  "dependencies": [
    "@eslint/compat",
    "@next/eslint-plugin-next",
    "eslint",
    "eslint-config-next",
    "eslint-config-prettier",
    "eslint-plugin-import",
    "eslint-plugin-jsx-a11y",
    "eslint-plugin-prettier",
    "eslint-plugin-react",
    "eslint-plugin-react-compiler",
    "eslint-plugin-react-hooks",
    "prettier",
    "prettier-plugin-tailwindcss",
    "typescript",
    "typescript-eslint"
  ],
  "files": [
    {
      "path": "eslint.config.mjs",
      "content": "import globals from \"globals\";\r\nimport tseslint from \"typescript-eslint\";\r\nimport eslintPluginReact from \"eslint-plugin-react\";\r\nimport eslintPluginReactHooks from \"eslint-plugin-react-hooks\";\r\nimport {fixupPluginRules} from \"@eslint/compat\";\r\nimport eslintPluginPrettier from \"eslint-plugin-prettier/recommended\";\r\nimport eslintPluginImport from \"eslint-plugin-import\";\r\nimport eslintPluginReactCompiler from \"eslint-plugin-react-compiler\";\r\nimport eslintPluginNext from \"@next/eslint-plugin-next\";\r\nimport eslintPluginJsxA11y from \"eslint-plugin-jsx-a11y\";\r\n\r\nexport default [\r\n  // Ignores configuration\r\n  {\r\n    ignores: [\"node_modules\", \".next\", \"out\", \"coverage\", \".idea\"],\r\n  },\r\n  // General configuration\r\n  {\r\n    rules: {\r\n      \"padding-line-between-statements\": [\r\n        \"warn\",\r\n        {blankLine: \"always\", prev: \"*\", next: [\"return\", \"export\"]},\r\n        {blankLine: \"always\", prev: [\"const\", \"let\", \"var\"], next: \"*\"},\r\n        {blankLine: \"any\", prev: [\"const\", \"let\", \"var\"], next: [\"const\", \"let\", \"var\"]},\r\n      ],\r\n      \"no-console\": [\"warn\", {allow: [\"error\"]}],\r\n    },\r\n  },\r\n  // React configuration\r\n  {\r\n    plugins: {\r\n      react: fixupPluginRules(eslintPluginReact),\r\n      \"react-hooks\": fixupPluginRules(eslintPluginReactHooks),\r\n      \"react-compiler\": fixupPluginRules(eslintPluginReactCompiler),\r\n      \"jsx-a11y\": fixupPluginRules(eslintPluginJsxA11y),\r\n    },\r\n    languageOptions: {\r\n      parserOptions: {\r\n        ecmaFeatures: {\r\n          jsx: true,\r\n        },\r\n      },\r\n      globals: {\r\n        ...globals.browser,\r\n        ...globals.serviceworker,\r\n      },\r\n    },\r\n    settings: {\r\n      react: {\r\n        version: \"detect\",\r\n      },\r\n    },\r\n    rules: {\r\n      ...eslintPluginReact.configs.recommended.rules,\r\n      ...eslintPluginJsxA11y.configs.recommended.rules,\r\n      ...eslintPluginReactHooks.configs.recommended.rules,\r\n      \"react/jsx-boolean-value\": [\"error\", \"never\"],\r\n      \"react/jsx-curly-brace-presence\": [\"error\", {props: \"never\", children: \"never\"}],\r\n      \"react/jsx-no-useless-fragment\": \"error\",\r\n      \"react/prop-types\": \"off\",\r\n      \"react/jsx-uses-react\": \"off\",\r\n      \"react/no-array-index-key\": \"off\",\r\n      \"react/react-in-jsx-scope\": \"off\",\r\n      \"react/self-closing-comp\": \"warn\",\r\n      \"react/jsx-sort-props\": [\r\n        \"warn\",\r\n        {\r\n          callbacksLast: true,\r\n          shorthandFirst: true,\r\n          noSortAlphabetically: false,\r\n          reservedFirst: true,\r\n        },\r\n      ],\r\n      \"react-compiler/react-compiler\": \"error\",\r\n      \"react/jsx-no-leaked-render\": \"off\",\r\n      \"jsx-a11y/no-static-element-interactions\": \"off\",\r\n      \"jsx-a11y/click-events-have-key-events\": \"off\",\r\n      \"jsx-a11y/html-has-lang\": \"off\",\r\n    },\r\n  },\r\n  // TypeScript configuration\r\n  ...[\r\n    ...tseslint.configs.recommended,\r\n    {\r\n      rules: {\r\n        \"@typescript-eslint/ban-ts-comment\": \"off\",\r\n        \"@typescript-eslint/no-empty-object-type\": \"error\",\r\n        \"@typescript-eslint/no-unsafe-function-type\": \"error\",\r\n        \"@typescript-eslint/no-wrapper-object-types\": \"error\",\r\n        \"@typescript-eslint/no-empty-function\": \"off\",\r\n        \"@typescript-eslint/no-explicit-any\": \"off\",\r\n        \"@typescript-eslint/no-inferrable-types\": \"off\",\r\n        \"@typescript-eslint/no-namespace\": \"off\",\r\n        \"@typescript-eslint/no-non-null-assertion\": \"off\",\r\n        \"@typescript-eslint/no-shadow\": \"off\",\r\n        \"@typescript-eslint/explicit-function-return-type\": \"off\",\r\n        \"@typescript-eslint/require-await\": \"off\",\r\n        \"@typescript-eslint/no-floating-promises\": \"off\",\r\n        \"@typescript-eslint/no-confusing-void-expression\": \"off\",\r\n        \"@typescript-eslint/no-unused-vars\": [\r\n          \"warn\",\r\n          {\r\n            args: \"after-used\",\r\n            ignoreRestSiblings: false,\r\n            argsIgnorePattern: \"^_.*?$\",\r\n            caughtErrorsIgnorePattern: \"^_.*?$\",\r\n          },\r\n        ],\r\n      },\r\n    },\r\n  ],\r\n  // Prettier configuration\r\n  ...[\r\n    eslintPluginPrettier,\r\n    {\r\n      rules: {\r\n        \"prettier/prettier\": [\r\n          \"warn\",\r\n          {\r\n            printWidth: 100,\r\n            trailingComma: \"all\",\r\n            tabWidth: 2,\r\n            semi: true,\r\n            singleQuote: false,\r\n            bracketSpacing: false,\r\n            arrowParens: \"always\",\r\n            endOfLine: \"auto\",\r\n            plugins: [\"prettier-plugin-tailwindcss\"],\r\n          },\r\n        ],\r\n      },\r\n    },\r\n  ],\r\n  // Import configuration\r\n  {\r\n    plugins: {\r\n      import: fixupPluginRules(eslintPluginImport),\r\n    },\r\n    rules: {\r\n      \"import/no-default-export\": \"off\",\r\n      \"import/order\": [\r\n        \"warn\",\r\n        {\r\n          groups: [\r\n            \"type\",\r\n            \"builtin\",\r\n            \"object\",\r\n            \"external\",\r\n            \"internal\",\r\n            \"parent\",\r\n            \"sibling\",\r\n            \"index\",\r\n          ],\r\n          pathGroups: [\r\n            {\r\n              pattern: \"@/*\",\r\n              group: \"external\",\r\n              position: \"after\",\r\n            },\r\n          ],\r\n          \"newlines-between\": \"always\",\r\n        },\r\n      ],\r\n    },\r\n  },\r\n  // Next configuration\r\n  {\r\n    plugins: {\r\n      \"@next/next\": fixupPluginRules(eslintPluginNext),\r\n    },\r\n    languageOptions: {\r\n      globals: {\r\n        ...globals.node,\r\n        ...globals.browser,\r\n      },\r\n    },\r\n    rules: {\r\n      ...eslintPluginNext.configs.recommended.rules,\r\n      \"@next/next/no-img-element\": \"off\",\r\n      \"@next/next/no-html-link-for-pages\": \"off\",\r\n    },\r\n  },\r\n];\r\n",
      "type": "registry:file",
      "target": "~/eslint.config.mjs"
    }
  ]
}